deepsweep/__init__.py
deepsweep/__main__.py
deepsweep/cli.py
deepsweep/cli_mcp.py
deepsweep/community.py
deepsweep/constants.py
deepsweep/exceptions.py
deepsweep/models.py
deepsweep/output.py
deepsweep/patterns.py
deepsweep/validator.py
deepsweep/commands/__init__.py
deepsweep/commands/badge.py
deepsweep/commands/doctor.py
deepsweep/commands/init.py
deepsweep/mcp/__init__.py
deepsweep/mcp/discovery.py
deepsweep/mcp/validator.py
deepsweep/telemetry/__init__.py
deepsweep/telemetry/config.py
deepsweep/telemetry/events.py
deepsweep/telemetry/threat.py
deepsweep/py.typed
deepsweep_ai-0.2.1.dist-info/METADATA
deepsweep_ai-0.2.1.dist-info/WHEEL
deepsweep_ai-0.2.1.dist-info/entry_points.txt
deepsweep_ai-0.2.1.dist-info/licenses/LICENSE
deepsweep_ai-0.2.1.dist-info/RECORD
