Metadata-Version: 2.4
Name: deepsweep-ai
Version: 0.2.1
Summary: Security Gateway for AI Coding Assistants. Validate Cursor, Copilot, Claude Code, Windsurf, and MCP configurations.
Project-URL: Homepage, https://deepsweep.ai
Project-URL: Documentation, https://docs.deepsweep.ai
Project-URL: Repository, https://github.com/deepsweep-ai/deepsweep
Project-URL: Changelog, https://github.com/deepsweep-ai/deepsweep/blob/main/CHANGELOG.md
Project-URL: Issues, https://github.com/deepsweep-ai/deepsweep/issues
Author-email: DeepSweep <security@deepsweep.ai>
Maintainer-email: DeepSweep <security@deepsweep.ai>
License: MIT
License-File: LICENSE
Keywords: ai,claude,copilot,cursor,linting,mcp,security,validation,vibe-coding,windsurf
Classifier: Development Status :: 5 - Production/Stable
Classifier: Environment :: Console
Classifier: Intended Audience :: Developers
Classifier: License :: OSI Approved :: MIT License
Classifier: Operating System :: OS Independent
Classifier: Programming Language :: Python :: 3
Classifier: Programming Language :: Python :: 3.10
Classifier: Programming Language :: Python :: 3.11
Classifier: Programming Language :: Python :: 3.12
Classifier: Programming Language :: Python :: 3.13
Classifier: Topic :: Security
Classifier: Topic :: Software Development :: Quality Assurance
Classifier: Typing :: Typed
Requires-Python: >=3.10
Requires-Dist: click>=8.1.0
Requires-Dist: posthog>=3.0.0
Requires-Dist: pydantic>=2.0.0
Requires-Dist: pyyaml>=6.0
Requires-Dist: rich>=13.0.0
Provides-Extra: dev
Requires-Dist: mypy>=1.0.0; extra == 'dev'
Requires-Dist: pre-commit>=3.0.0; extra == 'dev'
Requires-Dist: pytest-cov>=4.0.0; extra == 'dev'
Requires-Dist: pytest-xdist>=3.0.0; extra == 'dev'
Requires-Dist: pytest>=8.0.0; extra == 'dev'
Requires-Dist: ruff>=0.1.0; extra == 'dev'
Provides-Extra: docs
Requires-Dist: mkdocs-material>=9.0.0; extra == 'docs'
Requires-Dist: mkdocs>=1.5.0; extra == 'docs'
